isogeocoder/__init__.py
isogeocoder/geo.py
isogeocoder/iso.py
isogeocoder-0.0.1.dist-info/LICENSE
isogeocoder-0.0.1.dist-info/METADATA
isogeocoder-0.0.1.dist-info/WHEEL
isogeocoder-0.0.1.dist-info/top_level.txt
isogeocoder-0.0.1.dist-info/RECORD
