Metadata-Version: 2.1
Name: isogeocoder
Version: 0.0.1
Summary: isogeocoder is a tool that generates and assigns standardized iso compliant unique identification numbers or codes for entities based on location information. It can create and assign codes based on a country's administrative division (geo-location) or any administrative level depending on the use case.
Home-page: https://github.com/MBSSE-SL/isogeocoder
Author: David Moinina Sengeh, Mohamed James,Mosses TF Vibbe
Author-email: dsengeh@gmail.com, mohamedjames21@gmail.com, vbmo2007@gmail.com
Project-URL: Bug Tracker, https://github.com/MBSSE-SL/isogeocoder/issues
Classifier: Programming Language :: Python :: 3
Classifier: License :: OSI Approved :: MIT License
Classifier: Operating System :: OS Independent
Requires-Python: >=3.6
License-File: LICENSE
